{
  "info": {
    "_postman_id": "2920d145-bb36-4f49-b84f-19e8dd026806",
    "name": "Loan Collection Management System",
    "schema": "https://schema.getpostman.com/json/collection/v2.1.0/collection.json",
    "_exporter_id": "25689015",
    "_collection_link": "https://go.postman.co/collection/25689015-2920d145-bb36-4f49-b84f-19e8dd026806?source=collection_link"
  },
  "item": [
    {
      "name": "Login",
      "request": {
        "method": "POST",
        "header": [
          {
            "key": "Accept",
            "value": "application/json",
            "type": "text"
          },
          {
            "key": "Content-Type",
            "value": "application/json",
            "type": "text"
          }
        ],
        "body": {
          "mode": "raw",
          "raw": "{\n    // for admin access use this login\n    \"email\": \"admin@loanapp.com\",\n    \"password\": \"Admin@1234\"\n\n    // \"email\": \"ravi@loanapp.com\",\n    // \"password\": \"Agent@1234\"\n}",
          "options": {
            "raw": {
              "language": "json"
            }
          }
        },
        "url": {
          "raw": "http://127.0.0.1:8000/api/auth/login",
          "protocol": "http",
          "host": [
            "127",
            "0",
            "0",
            "1"
          ],
          "port": "8000",
          "path": [
            "api",
            "auth",
            "login"
          ]
        }
      },
      "response": []
    },
    {
      "name": "Logout",
      "request": {
        "auth": {
          "type": "bearer",
          "bearer": [
            {
              "key": "token",
              "value": "2|vWPZug8h0lVbMemVpWxpbIhNej1aduuBNVEbqu0m2548ec53",
              "type": "string"
            }
          ]
        },
        "method": "POST",
        "header": [],
        "body": {
          "mode": "raw",
          "raw": "",
          "options": {
            "raw": {
              "language": "json"
            }
          }
        },
        "url": {
          "raw": "http://127.0.0.1:8000/api/auth/logout",
          "protocol": "http",
          "host": [
            "127",
            "0",
            "0",
            "1"
          ],
          "port": "8000",
          "path": [
            "api",
            "auth",
            "logout"
          ]
        }
      },
      "response": []
    },
    {
      "name": "Create Loans",
      "request": {
        "auth": {
          "type": "bearer",
          "bearer": [
            {
              "key": "token",
              "value": "1|LyzsblOxXcbiKfvaO1Gayo9m65Bj5JNK9poAJdxN48018f46",
              "type": "string"
            }
          ]
        },
        "method": "POST",
        "header": [],
        "body": {
          "mode": "raw",
          "raw": "{\n    \"customer_name\": \"Akku Sharma\",\n    \"mobile\": \"9876543210\",\n    \"address\": \"123 Main Street, Mumbai\",\n    \"loan_amount\": 50000,\n    \"emi_amount\": 5000,\n    \"tenure_months\": 12,\n    \"disbursed_at\": \"2024-01-01\",\n    \"first_emi_date\": \"2024-02-01\"\n}",
          "options": {
            "raw": {
              "language": "json"
            }
          }
        },
        "url": {
          "raw": "http://127.0.0.1:8000/api/loans",
          "protocol": "http",
          "host": [
            "127",
            "0",
            "0",
            "1"
          ],
          "port": "8000",
          "path": [
            "api",
            "loans"
          ]
        }
      },
      "response": []
    },
    {
      "name": "Get Loans",
      "request": {
        "auth": {
          "type": "bearer",
          "bearer": [
            {
              "key": "token",
              "value": "1|LyzsblOxXcbiKfvaO1Gayo9m65Bj5JNK9poAJdxN48018f46",
              "type": "string"
            }
          ]
        },
        "method": "GET",
        "header": [],
        "url": {
          "raw": "http://127.0.0.1:8000/api/loans",
          "protocol": "http",
          "host": [
            "127",
            "0",
            "0",
            "1"
          ],
          "port": "8000",
          "path": [
            "api",
            "loans"
          ]
        }
      },
      "response": []
    },
    {
      "name": "Get Single Loan",
      "request": {
        "auth": {
          "type": "bearer",
          "bearer": [
            {
              "key": "token",
              "value": "1|LyzsblOxXcbiKfvaO1Gayo9m65Bj5JNK9poAJdxN48018f46",
              "type": "string"
            }
          ]
        },
        "method": "GET",
        "header": [],
        "url": {
          "raw": "http://127.0.0.1:8000/api/loans/1",
          "protocol": "http",
          "host": [
            "127",
            "0",
            "0",
            "1"
          ],
          "port": "8000",
          "path": [
            "api",
            "loans",
            "1"
          ]
        }
      },
      "response": []
    },
    {
      "name": "Update Only Status through Put",
      "request": {
        "auth": {
          "type": "bearer",
          "bearer": [
            {
              "key": "token",
              "value": "1|LyzsblOxXcbiKfvaO1Gayo9m65Bj5JNK9poAJdxN48018f46",
              "type": "string"
            }
          ]
        },
        "method": "PUT",
        "header": [],
        "body": {
          "mode": "raw",
          "raw": "{\n    \"status\": \"closed\"\n}",
          "options": {
            "raw": {
              "language": "json"
            }
          }
        },
        "url": {
          "raw": "http://127.0.0.1:8000/api/loans/1",
          "protocol": "http",
          "host": [
            "127",
            "0",
            "0",
            "1"
          ],
          "port": "8000",
          "path": [
            "api",
            "loans",
            "1"
          ]
        }
      },
      "response": []
    },
    {
      "name": "Add Collections",
      "request": {
        "auth": {
          "type": "bearer",
          "bearer": [
            {
              "key": "token",
              "value": "1|LyzsblOxXcbiKfvaO1Gayo9m65Bj5JNK9poAJdxN48018f46",
              "type": "string"
            }
          ]
        },
        "method": "POST",
        "header": [],
        "body": {
          "mode": "raw",
          "raw": "{\n    \"loan_id\": 1,\n    \"amount_paid\": 500,\n    \"payment_mode\": \"cash\",\n    \"location\": \"Mumbai\",\n    \"collected_at\": \"2026-05-16 10:30:00\",\n    \"remarks\": \"Test today collection\"\n}",
          "options": {
            "raw": {
              "language": "json"
            }
          }
        },
        "url": {
          "raw": "http://127.0.0.1:8000/api/collections",
          "protocol": "http",
          "host": [
            "127",
            "0",
            "0",
            "1"
          ],
          "port": "8000",
          "path": [
            "api",
            "collections"
          ]
        }
      },
      "response": []
    },
    {
      "name": "Get Collections",
      "request": {
        "auth": {
          "type": "bearer",
          "bearer": [
            {
              "key": "token",
              "value": "1|LyzsblOxXcbiKfvaO1Gayo9m65Bj5JNK9poAJdxN48018f46",
              "type": "string"
            }
          ]
        },
        "method": "GET",
        "header": [],
        "url": {
          "raw": "http://127.0.0.1:8000/api/collections",
          "protocol": "http",
          "host": [
            "127",
            "0",
            "0",
            "1"
          ],
          "port": "8000",
          "path": [
            "api",
            "collections"
          ]
        }
      },
      "response": []
    },
    {
      "name": "Get Single Collection",
      "request": {
        "auth": {
          "type": "bearer",
          "bearer": [
            {
              "key": "token",
              "value": "1|LyzsblOxXcbiKfvaO1Gayo9m65Bj5JNK9poAJdxN48018f46",
              "type": "string"
            }
          ]
        },
        "method": "GET",
        "header": [],
        "url": {
          "raw": "http://127.0.0.1:8000/api/collections/1",
          "protocol": "http",
          "host": [
            "127",
            "0",
            "0",
            "1"
          ],
          "port": "8000",
          "path": [
            "api",
            "collections",
            "1"
          ]
        }
      },
      "response": []
    },
    {
      "name": "http://127.0.0.1:8000/api/collections",
      "request": {
        "auth": {
          "type": "bearer",
          "bearer": [
            {
              "key": "token",
              "value": "3|IHcPdXyrs6M3boUhtNrnGE8TNiMX6vrteIrNBgN86cdee32f",
              "type": "string"
            }
          ]
        },
        "method": "POST",
        "header": [
          {
            "key": "Accept",
            "value": "application/json",
            "type": "text"
          }
        ],
        "body": {
          "mode": "raw",
          "raw": "{\n    \"loan_id\": 1,\n    \"amount_paid\": 999999,\n    \"payment_mode\": \"cash\"\n}",
          "options": {
            "raw": {
              "language": "json"
            }
          }
        },
        "url": {
          "raw": "http://127.0.0.1:8000/api/collections",
          "protocol": "http",
          "host": [
            "127",
            "0",
            "0",
            "1"
          ],
          "port": "8000",
          "path": [
            "api",
            "collections"
          ]
        }
      },
      "response": []
    },
    {
      "name": "Dashboard",
      "request": {
        "auth": {
          "type": "bearer",
          "bearer": [
            {
              "key": "token",
              "value": "1|LyzsblOxXcbiKfvaO1Gayo9m65Bj5JNK9poAJdxN48018f46",
              "type": "string"
            }
          ]
        },
        "method": "GET",
        "header": [],
        "url": {
          "raw": "http://127.0.0.1:8000/api/dashboard",
          "protocol": "http",
          "host": [
            "127",
            "0",
            "0",
            "1"
          ],
          "port": "8000",
          "path": [
            "api",
            "dashboard"
          ]
        }
      },
      "response": []
    },
    {
      "name": "Prediction",
      "request": {
        "auth": {
          "type": "bearer",
          "bearer": [
            {
              "key": "token",
              "value": "1|LyzsblOxXcbiKfvaO1Gayo9m65Bj5JNK9poAJdxN48018f46",
              "type": "string"
            }
          ]
        },
        "method": "GET",
        "header": [],
        "url": {
          "raw": "http://127.0.0.1:8000/api/dashboard/prediction",
          "protocol": "http",
          "host": [
            "127",
            "0",
            "0",
            "1"
          ],
          "port": "8000",
          "path": [
            "api",
            "dashboard",
            "prediction"
          ]
        }
      },
      "response": []
    }
  ]
}